{
  "fetched_date": "2026-05-13",
  "method": "web_scrape",
  "total_ads": 74,
  "competitors": {
    "Enna": [
      {
        "competitor": "Enna",
        "ad_id": "1868277354563662",
        "status": "Active",
        "page_name": "enna.care",
        "ad_copy": "Mit enna bleiben Generationen verbunden: \u2705 Erinnerungen schicken \u2705 Gro\u00dfe Auswahl an Unterhaltung",
        "headline": "Kein Kauf, keine Einrichtung.",
        "cta": null,
        "platforms": [],
        "impression_lower": null,
        "impression_upper": null,
        "start_date": "2025-11-14",
        "stop_date": null,
        "days_running": 180
      },
      {
        "competitor": "Enna",
        "ad_id": "1362684515702149",
        "status": "Active",
        "page_name": "enna.care",
        "ad_copy": "Mit enna bleiben Generationen verbunden: \u2705 Erinnerungen schicken \u2705 Gro\u00dfe Auswahl an Unterhaltung",
        "headline": "Kein Kauf, keine Einrichtung.",
        "cta": null,
        "platforms": [],
        "impression_lower": null,
        "impression_upper": null,
        "start_date": "2026-04-28",
        "stop_date": null,
        "days_running": 15
      },
      {
        "competitor": "Enna",
        "ad_id": "1938930663325095",
        "status": "Active",
        "page_name": "enna.care",
        "ad_copy": "Mit enna bleiben Generationen verbunden: \u2705 Erinnerungen schicken \u2705 Gro\u00dfe Auswahl an Unterhaltung",
        "headline": "Kein Kauf, keine Einrichtung.",
        "cta": null,
        "platforms": [],
        "impression_lower": null,
        "impression_upper": null,
        "start_date": "2025-11-14",
        "stop_date": null,
        "days_running": 180
      },
      {
        "competitor": "Enna",
        "ad_id": "1852060685669387",
        "status": "Active",
        "page_name": "enna.care",
        "ad_copy": "Mit enna bleiben Generationen verbunden: \u2705 Erinnerungen schicken \u2705 Gro\u00dfe Auswahl an Unterhaltung",
        "headline": "Kein Kauf, keine Einrichtung.",
        "cta": null,
        "platforms": [],
        "impression_lower": null,
        "impression_upper": null,
        "start_date": "2025-11-07",
        "stop_date": null,
        "days_running": 187
      },
      {
        "competitor": "Enna",
        "ad_id": "1296748252140081",
        "status": "Active",
        "page_name": "enna.care",
        "ad_copy": "Mit enna bleiben Generationen verbunden: \u2705 Erinnerungen schicken \u2705 Gro\u00dfe Auswahl an Unterhaltung",
        "headline": "Kein Kauf, keine Einrichtung.",
        "cta": null,
        "platforms": [],
        "impression_lower": null,
        "impression_upper": null,
        "start_date": "2025-11-07",
        "stop_date": null,
        "days_running": 187
      },
      {
        "competitor": "Enna",
        "ad_id": "841302105060560",
        "status": "Active",
        "page_name": "enna.care",
        "ad_copy": "Mit enna bleiben Generationen verbunden: \u2705 Erinnerungen schicken \u2705 Gro\u00dfe Auswahl an Unterhaltung",
        "headline": "Kein Kauf, keine Einrichtung.",
        "cta": null,
        "platforms": [],
        "impression_lower": null,
        "impression_upper": null,
        "start_date": "2025-11-07",
        "stop_date": null,
        "days_running": 187
      },
      {
        "competitor": "Enna",
        "ad_id": "3976129939359406",
        "status": "Active",
        "page_name": "enna.care",
        "ad_copy": "Mit enna bleiben Generationen verbunden: \u2705 Erinnerungen schicken \u2705 Gro\u00dfe Auswahl an Unterhaltung",
        "headline": "Kein Kauf, keine Einrichtung.",
        "cta": null,
        "platforms": [],
        "impression_lower": null,
        "impression_upper": null,
        "start_date": "2025-11-07",
        "stop_date": null,
        "days_running": 187
      },
      {
        "competitor": "Enna",
        "ad_id": "1588345672369492",
        "status": "Active",
        "page_name": "enna.care",
        "ad_copy": "Mit enna bleiben Generationen verbunden: \u2705 Erinnerungen schicken \u2705 Gro\u00dfe Auswahl an Unterhaltung",
        "headline": "Kein Kauf, keine Einrichtung.",
        "cta": null,
        "platforms": [],
        "impression_lower": null,
        "impression_upper": null,
        "start_date": "2026-02-11",
        "stop_date": null,
        "days_running": 91
      },
      {
        "competitor": "Enna",
        "ad_id": "1177236264536592",
        "status": "Active",
        "page_name": "enna.care",
        "ad_copy": "Mach auch deine Oma gl\u00fccklich & bring die ganze Familie n\u00e4her zusammen! \ud83e\udd70 \u2705 Erinnerungen & Nachrichten schicken \u2705 Gro\u00dfe Auswahl an Unterhaltung",
        "headline": "Kein Kauf, keine Einrichtung.",
        "cta": null,
        "platforms": [],
        "impression_lower": null,
        "impression_upper": null,
        "start_date": "2025-12-22",
        "stop_date": null,
        "days_running": 142
      },
      {
        "competitor": "Enna",
        "ad_id": "1943193019573119",
        "status": "Active",
        "page_name": "enna.care",
        "ad_copy": "Mit enna bleiben Generationen verbunden: \u2705 Erinnerungen schicken \u2705 Gro\u00dfe Auswahl an Unterhaltung",
        "headline": "Kein Kauf, keine Einrichtung.",
        "cta": null,
        "platforms": [],
        "impression_lower": null,
        "impression_upper": null,
        "start_date": "2025-11-07",
        "stop_date": null,
        "days_running": 187
      },
      {
        "competitor": "Enna",
        "ad_id": "4072587919646468",
        "status": "Active",
        "page_name": "enna.care",
        "ad_copy": "Mit enna bleiben Generationen verbunden: \u2705 Erinnerungen schicken \u2705 Gro\u00dfe Auswahl an Unterhaltung",
        "headline": "Kein Kauf, keine Einrichtung.",
        "cta": null,
        "platforms": [],
        "impression_lower": null,
        "impression_upper": null,
        "start_date": "2026-04-12",
        "stop_date": null,
        "days_running": 31
      },
      {
        "competitor": "Enna",
        "ad_id": "2260190851070799",
        "status": "Active",
        "page_name": "enna.care",
        "ad_copy": "Mit enna bleiben Generationen verbunden: \u2705 Erinnerungen schicken \u2705 Gro\u00dfe Auswahl an Unterhaltung",
        "headline": "Kein Kauf, keine Einrichtung.",
        "cta": null,
        "platforms": [],
        "impression_lower": null,
        "impression_upper": null,
        "start_date": "2025-11-14",
        "stop_date": null,
        "days_running": 180
      },
      {
        "competitor": "Enna",
        "ad_id": "1630159098158899",
        "status": "Active",
        "page_name": "enna.care",
        "ad_copy": "\u2764\ufe0f 30.000+ Nutzer \ud83d\udcac 4000+ Bewertungen \u2b50\ufe0f 4,7 Sterne Bewertung",
        "headline": "\u2b50\ufe0f 4,7 Sterne Bewertung",
        "cta": "Learn More",
        "platforms": [],
        "impression_lower": null,
        "impression_upper": null,
        "start_date": "2025-12-22",
        "stop_date": null,
        "days_running": 142
      },
      {
        "competitor": "Enna",
        "ad_id": "796404973298946",
        "status": "Active",
        "page_name": "enna.care",
        "ad_copy": "Mit enna bleiben Generationen verbunden: \u2705 Erinnerungen schicken \u2705 Gro\u00dfe Auswahl an Unterhaltung",
        "headline": "Kein Kauf, keine Einrichtung.",
        "cta": null,
        "platforms": [],
        "impression_lower": null,
        "impression_upper": null,
        "start_date": "2025-11-07",
        "stop_date": null,
        "days_running": 187
      },
      {
        "competitor": "Enna",
        "ad_id": "966816482430409",
        "status": "Active",
        "page_name": "enna.care",
        "ad_copy": "Mach auch deine Oma gl\u00fccklich & bring die ganze Familie n\u00e4her zusammen! \ud83e\udd70 \u2705 Erinnerungen & Nachrichten schicken \u2705 Gro\u00dfe Auswahl an Unterhaltung",
        "headline": "Kein Kauf, keine Einrichtung.",
        "cta": null,
        "platforms": [],
        "impression_lower": null,
        "impression_upper": null,
        "start_date": "2026-04-22",
        "stop_date": null,
        "days_running": 21
      },
      {
        "competitor": "Enna",
        "ad_id": "3727759467519562",
        "status": "Active",
        "page_name": "enna.care",
        "ad_copy": "Mit enna bleiben Generationen verbunden: \u2705 Erinnerungen schicken \u2705 Gro\u00dfe Auswahl an Unterhaltung",
        "headline": "Kein Kauf, keine Einrichtung.",
        "cta": null,
        "platforms": [],
        "impression_lower": null,
        "impression_upper": null,
        "start_date": "2025-11-14",
        "stop_date": null,
        "days_running": 180
      },
      {
        "competitor": "Enna",
        "ad_id": "933151279692839",
        "status": "Active",
        "page_name": "enna.care",
        "ad_copy": "Mach auch deine Oma gl\u00fccklich & bring die ganze Familie n\u00e4her zusammen! \ud83e\udd70 \u2705 Erinnerungen & Nachrichten schicken \u2705 Gro\u00dfe Auswahl an Unterhaltung",
        "headline": "Kein Kauf, keine Einrichtung.",
        "cta": null,
        "platforms": [],
        "impression_lower": null,
        "impression_upper": null,
        "start_date": "2026-04-22",
        "stop_date": null,
        "days_running": 21
      },
      {
        "competitor": "Enna",
        "ad_id": "850477457839087",
        "status": "Active",
        "page_name": "enna.care",
        "ad_copy": "Mach Oma & Opa gl\u00fccklich!\ud83e\udef6 \u27a1\ufe0f Jetzt 120\u20ac sparen! (Gilt nur f\u00fcr kurze Zeit) Das perfekte Geschenk f\u00fcr Oma & Opa ! \ud83d\udc9d",
        "headline": "Das perfekte Geschenk f\u00fcr Oma & Opa ! \ud83d\udc9d",
        "cta": "Learn More",
        "platforms": [],
        "impression_lower": null,
        "impression_upper": null,
        "start_date": "2025-12-22",
        "stop_date": null,
        "days_running": 142
      },
      {
        "competitor": "Enna",
        "ad_id": "1549478262721918",
        "status": "Active",
        "page_name": "enna.care",
        "ad_copy": "Mit enna bleiben Generationen verbunden: \u2705 Erinnerungen schicken \u2705 Gro\u00dfe Auswahl an Unterhaltung",
        "headline": "Kein Kauf, keine Einrichtung.",
        "cta": null,
        "platforms": [],
        "impression_lower": null,
        "impression_upper": null,
        "start_date": "2025-11-07",
        "stop_date": null,
        "days_running": 187
      },
      {
        "competitor": "Enna",
        "ad_id": "2040130603507445",
        "status": "Active",
        "page_name": "enna.care",
        "ad_copy": "Mach auch deine Oma gl\u00fccklich & bring die ganze Familie n\u00e4her zusammen! \ud83e\udd70 \u2705 Erinnerungen & Nachrichten schicken \u2705 Gro\u00dfe Auswahl an Unterhaltung",
        "headline": "Kein Kauf, keine Einrichtung.",
        "cta": null,
        "platforms": [],
        "impression_lower": null,
        "impression_upper": null,
        "start_date": "2025-12-22",
        "stop_date": null,
        "days_running": 142
      },
      {
        "competitor": "Enna",
        "ad_id": "1171548231746967",
        "status": "Active",
        "page_name": "enna.care",
        "ad_copy": "Mit enna bleiben Generationen verbunden: \u2705 Erinnerungen schicken \u2705 Gro\u00dfe Auswahl an Unterhaltung",
        "headline": "Kein Kauf, keine Einrichtung.",
        "cta": null,
        "platforms": [],
        "impression_lower": null,
        "impression_upper": null,
        "start_date": "2025-11-15",
        "stop_date": null,
        "days_running": 179
      },
      {
        "competitor": "Enna",
        "ad_id": "871339118687590",
        "status": "Active",
        "page_name": "enna.care",
        "ad_copy": "Mach auch deine Oma gl\u00fccklich & bring die ganze Familie n\u00e4her zusammen! \ud83e\udd70 \u2705 Erinnerungen & Nachrichten schicken \u2705 Gro\u00dfe Auswahl an Unterhaltung",
        "headline": "Kein Kauf, keine Einrichtung.",
        "cta": null,
        "platforms": [],
        "impression_lower": null,
        "impression_upper": null,
        "start_date": "2026-01-22",
        "stop_date": null,
        "days_running": 111
      },
      {
        "competitor": "Enna",
        "ad_id": "2761672647588250",
        "status": "Active",
        "page_name": "enna.care",
        "ad_copy": "Mit enna bleiben Generationen verbunden: \u2705 Erinnerungen schicken \u2705 Gro\u00dfe Auswahl an Unterhaltung",
        "headline": "Kein Kauf, keine Einrichtung.",
        "cta": null,
        "platforms": [],
        "impression_lower": null,
        "impression_upper": null,
        "start_date": "2026-02-11",
        "stop_date": null,
        "days_running": 91
      },
      {
        "competitor": "Enna",
        "ad_id": "1196762821852142",
        "status": "Active",
        "page_name": "enna.care",
        "ad_copy": "\u2764\ufe0f 30.000+ Nutzer \ud83d\udcac 4000+ Bewertungen \u2b50\ufe0f 4,7 Sterne Bewertung",
        "headline": "\u2b50\ufe0f 4,7 Sterne Bewertung",
        "cta": "Learn More",
        "platforms": [],
        "impression_lower": null,
        "impression_upper": null,
        "start_date": "2025-12-22",
        "stop_date": null,
        "days_running": 142
      },
      {
        "competitor": "Enna",
        "ad_id": "26604726072519208",
        "status": "Active",
        "page_name": "enna.care",
        "ad_copy": "Mach auch deine Oma gl\u00fccklich & bring die ganze Familie n\u00e4her zusammen! \ud83e\udd70 \u2705 Erinnerungen & Nachrichten schicken \u2705 Gro\u00dfe Auswahl an Unterhaltung",
        "headline": "Kein Kauf, keine Einrichtung.",
        "cta": null,
        "platforms": [],
        "impression_lower": null,
        "impression_upper": null,
        "start_date": "2026-04-22",
        "stop_date": null,
        "days_running": 21
      },
      {
        "competitor": "Enna",
        "ad_id": "3888948801242426",
        "status": "Active",
        "page_name": "enna.care",
        "ad_copy": "Mach auch deine Oma gl\u00fccklich & bring die ganze Familie n\u00e4her zusammen! \ud83e\udd70 \u2705 Erinnerungen & Nachrichten schicken \u2705 Gro\u00dfe Auswahl an Unterhaltung",
        "headline": "Kein Kauf, keine Einrichtung.",
        "cta": null,
        "platforms": [],
        "impression_lower": null,
        "impression_upper": null,
        "start_date": "2026-04-23",
        "stop_date": null,
        "days_running": 20
      },
      {
        "competitor": "Enna",
        "ad_id": "804595359053733",
        "status": "Active",
        "page_name": "enna.care",
        "ad_copy": "Mit enna bleiben Generationen verbunden: \u2705 Erinnerungen schicken \u2705 Gro\u00dfe Auswahl an Unterhaltung",
        "headline": "Kein Kauf, keine Einrichtung.",
        "cta": null,
        "platforms": [],
        "impression_lower": null,
        "impression_upper": null,
        "start_date": "2025-11-14",
        "stop_date": null,
        "days_running": 180
      },
      {
        "competitor": "Enna",
        "ad_id": "1373162224393589",
        "status": "Active",
        "page_name": "enna.care",
        "ad_copy": "Mit enna bleiben Generationen verbunden: \u2705 Erinnerungen schicken \u2705 Gro\u00dfe Auswahl an Unterhaltung",
        "headline": "Kein Kauf, keine Einrichtung.",
        "cta": null,
        "platforms": [],
        "impression_lower": null,
        "impression_upper": null,
        "start_date": "2025-11-07",
        "stop_date": null,
        "days_running": 187
      },
      {
        "competitor": "Enna",
        "ad_id": "1896813954581984",
        "status": "Active",
        "page_name": "enna.care",
        "ad_copy": "Mit enna bleiben Generationen verbunden: \u2705 Erinnerungen schicken \u2705 Gro\u00dfe Auswahl an Unterhaltung",
        "headline": "Kein Kauf, keine Einrichtung.",
        "cta": null,
        "platforms": [],
        "impression_lower": null,
        "impression_upper": null,
        "start_date": "2025-11-07",
        "stop_date": null,
        "days_running": 187
      },
      {
        "competitor": "Enna",
        "ad_id": "2393916927736067",
        "status": "Active",
        "page_name": "enna.care",
        "ad_copy": "Mach auch deine Oma gl\u00fccklich & bring die ganze Familie n\u00e4her zusammen! \ud83e\udd70 \u2705 Erinnerungen & Nachrichten schicken \u2705 Gro\u00dfe Auswahl an Unterhaltung",
        "headline": "Kein Kauf, keine Einrichtung.",
        "cta": null,
        "platforms": [],
        "impression_lower": null,
        "impression_upper": null,
        "start_date": "2026-01-17",
        "stop_date": null,
        "days_running": 116
      },
      {
        "competitor": "Enna",
        "ad_id": "4246986475583692",
        "status": "Active",
        "page_name": "enna.care",
        "ad_copy": "Mit enna bleiben Generationen verbunden: \u2705 Erinnerungen schicken \u2705 Gro\u00dfe Auswahl an Unterhaltung",
        "headline": "Kein Kauf, keine Einrichtung.",
        "cta": null,
        "platforms": [],
        "impression_lower": null,
        "impression_upper": null,
        "start_date": "2025-11-07",
        "stop_date": null,
        "days_running": 187
      },
      {
        "competitor": "Enna",
        "ad_id": "1614923399526182",
        "status": "Active",
        "page_name": "enna.care",
        "ad_copy": "Mach auch deine Oma gl\u00fccklich & bring die ganze Familie n\u00e4her zusammen! \ud83e\udd70 \u2705 Erinnerungen & Nachrichten schicken \u2705 Gro\u00dfe Auswahl an Unterhaltung",
        "headline": "Kein Kauf, keine Einrichtung.",
        "cta": null,
        "platforms": [],
        "impression_lower": null,
        "impression_upper": null,
        "start_date": "2026-02-10",
        "stop_date": null,
        "days_running": 92
      },
      {
        "competitor": "Enna",
        "ad_id": "779152008120335",
        "status": "Active",
        "page_name": "enna.care",
        "ad_copy": "Mit enna bleiben Generationen verbunden: \u2705 Erinnerungen schicken \u2705 Gro\u00dfe Auswahl an Unterhaltung",
        "headline": "Kein Kauf, keine Einrichtung.",
        "cta": null,
        "platforms": [],
        "impression_lower": null,
        "impression_upper": null,
        "start_date": "2026-02-26",
        "stop_date": null,
        "days_running": 76
      },
      {
        "competitor": "Enna",
        "ad_id": "1906464506615523",
        "status": "Active",
        "page_name": "enna.care",
        "ad_copy": "\u27a1\ufe0f Jetzt bestellen und unvergessliche Momente mit der Familie schaffen. \u27a1\ufe0f Einfach risikofrei 30 Tage kostenlos testen.",
        "headline": "\u27a1\ufe0f Einfach risikofrei 30 Tage kostenlos testen.",
        "cta": "Learn More",
        "platforms": [],
        "impression_lower": null,
        "impression_upper": null,
        "start_date": "2025-12-22",
        "stop_date": null,
        "days_running": 142
      },
      {
        "competitor": "Enna",
        "ad_id": "809944418627988",
        "status": "Active",
        "page_name": "enna.care",
        "ad_copy": "Mit enna bleiben Generationen verbunden: \u2705 Erinnerungen schicken \u2705 Gro\u00dfe Auswahl an Unterhaltung",
        "headline": "Kein Kauf, keine Einrichtung.",
        "cta": null,
        "platforms": [],
        "impression_lower": null,
        "impression_upper": null,
        "start_date": "2025-11-07",
        "stop_date": null,
        "days_running": 187
      },
      {
        "competitor": "Enna",
        "ad_id": "1473737363724928",
        "status": "Active",
        "page_name": "enna.care",
        "ad_copy": "\u2764\ufe0f 30.000+ Nutzer \ud83d\udcac 4000+ Bewertungen \u2b50\ufe0f 4,7 Sterne Bewertung",
        "headline": "Mache auch deine Gro\u00dfeltern gl\u00fccklich!\u2764\ufe0f",
        "cta": null,
        "platforms": [],
        "impression_lower": null,
        "impression_upper": null,
        "start_date": "2025-12-22",
        "stop_date": null,
        "days_running": 142
      },
      {
        "competitor": "Enna",
        "ad_id": "1628987998235230",
        "status": "Active",
        "page_name": "enna.care",
        "ad_copy": "Mit enna bleiben Generationen verbunden: \u2705 Erinnerungen schicken \u2705 Gro\u00dfe Auswahl an Unterhaltung",
        "headline": "Kein Kauf, keine Einrichtung.",
        "cta": null,
        "platforms": [],
        "impression_lower": null,
        "impression_upper": null,
        "start_date": "2026-02-25",
        "stop_date": null,
        "days_running": 77
      },
      {
        "competitor": "Enna",
        "ad_id": "25607802815471461",
        "status": "Active",
        "page_name": "enna.care",
        "ad_copy": "Mit enna bleiben Generationen verbunden: \u2705 Erinnerungen schicken \u2705 Gro\u00dfe Auswahl an Unterhaltung",
        "headline": "Kein Kauf, keine Einrichtung.",
        "cta": null,
        "platforms": [],
        "impression_lower": null,
        "impression_upper": null,
        "start_date": "2025-11-14",
        "stop_date": null,
        "days_running": 180
      },
      {
        "competitor": "Enna",
        "ad_id": "2337622166699478",
        "status": "Active",
        "page_name": "enna.care",
        "ad_copy": "Mit enna bleiben Generationen verbunden: \u2705 Erinnerungen schicken \u2705 Gro\u00dfe Auswahl an Unterhaltung",
        "headline": "Kein Kauf, keine Einrichtung.",
        "cta": null,
        "platforms": [],
        "impression_lower": null,
        "impression_upper": null,
        "start_date": "2025-11-14",
        "stop_date": null,
        "days_running": 180
      },
      {
        "competitor": "Enna",
        "ad_id": "2416502188853243",
        "status": "Active",
        "page_name": "enna.care",
        "ad_copy": "Mach auch deine Oma gl\u00fccklich & bring die ganze Familie n\u00e4her zusammen! \ud83e\udd70 \u2705 Erinnerungen & Nachrichten schicken \u2705 Gro\u00dfe Auswahl an Unterhaltung",
        "headline": "Kein Kauf, keine Einrichtung.",
        "cta": null,
        "platforms": [],
        "impression_lower": null,
        "impression_upper": null,
        "start_date": "2026-04-22",
        "stop_date": null,
        "days_running": 21
      },
      {
        "competitor": "Enna",
        "ad_id": "1154475496523141",
        "status": "Active",
        "page_name": "enna.care",
        "ad_copy": "Mach auch deine Oma gl\u00fccklich & bring die ganze Familie n\u00e4her zusammen! \ud83e\udd70 \u2705 Erinnerungen & Nachrichten schicken \u2705 Gro\u00dfe Auswahl an Unterhaltung",
        "headline": "Kein Kauf, keine Einrichtung.",
        "cta": null,
        "platforms": [],
        "impression_lower": null,
        "impression_upper": null,
        "start_date": "2026-01-16",
        "stop_date": null,
        "days_running": 117
      },
      {
        "competitor": "Enna",
        "ad_id": "2457105498055853",
        "status": "Active",
        "page_name": "enna.care",
        "ad_copy": "Jetzt enna 30 Tage kostenlos testen! \ud83c\udf81 Videocalls, Lieblingssendungen oder digitaler Terminkalender: enna holt die sch\u00f6nen Seiten moderner Technik ins Wohnzimmer deiner Gro\u00dfeltern \u2013 ganz ohne Technikstress. \u2728 Was enna m\u00f6glich macht:",
        "headline": "\u2705 Digitale Fotoalben f\u00fcr gemeinsame Momente",
        "cta": null,
        "platforms": [],
        "impression_lower": null,
        "impression_upper": null,
        "start_date": "2026-04-20",
        "stop_date": null,
        "days_running": 23
      },
      {
        "competitor": "Enna",
        "ad_id": "1262975262706273",
        "status": "Active",
        "page_name": "enna.care",
        "ad_copy": "\u27a1\ufe0f Jetzt bestellen und unvergessliche Momente mit der Familie schaffen. \u27a1\ufe0f Einfach risikofrei 30 Tage kostenlos testen.",
        "headline": "\u27a1\ufe0f Einfach risikofrei 30 Tage kostenlos testen.",
        "cta": "Learn More",
        "platforms": [],
        "impression_lower": null,
        "impression_upper": null,
        "start_date": "2026-04-22",
        "stop_date": null,
        "days_running": 21
      },
      {
        "competitor": "Enna",
        "ad_id": "848561304926655",
        "status": "Active",
        "page_name": "enna.care",
        "ad_copy": "Mach auch deine Oma gl\u00fccklich & bring die ganze Familie n\u00e4her zusammen! \ud83e\udd70 \u2705 Erinnerungen & Nachrichten schicken \u2705 Gro\u00dfe Auswahl an Unterhaltung",
        "headline": "Kein Kauf, keine Einrichtung.",
        "cta": null,
        "platforms": [],
        "impression_lower": null,
        "impression_upper": null,
        "start_date": "2026-04-22",
        "stop_date": null,
        "days_running": 21
      },
      {
        "competitor": "Enna",
        "ad_id": "1291640612869285",
        "status": "Active",
        "page_name": "enna.care",
        "ad_copy": "Mach auch deine Oma gl\u00fccklich & bring die ganze Familie n\u00e4her zusammen! \ud83e\udd70 \u2705 Erinnerungen & Nachrichten schicken \u2705 Gro\u00dfe Auswahl an Unterhaltung",
        "headline": "Kein Kauf, keine Einrichtung.",
        "cta": null,
        "platforms": [],
        "impression_lower": null,
        "impression_upper": null,
        "start_date": "2025-12-22",
        "stop_date": null,
        "days_running": 142
      },
      {
        "competitor": "Enna",
        "ad_id": "979071054807524",
        "status": "Active",
        "page_name": "enna.care",
        "ad_copy": "Mach auch deine Oma gl\u00fccklich & bring die ganze Familie n\u00e4her zusammen! \ud83e\udd70 \u2705 Erinnerungen & Nachrichten schicken \u2705 Gro\u00dfe Auswahl an Unterhaltung",
        "headline": "Kein Kauf, keine Einrichtung.",
        "cta": null,
        "platforms": [],
        "impression_lower": null,
        "impression_upper": null,
        "start_date": "2026-04-22",
        "stop_date": null,
        "days_running": 21
      },
      {
        "competitor": "Enna",
        "ad_id": "1226905979591545",
        "status": "Active",
        "page_name": "enna.care",
        "ad_copy": "Mit enna bleiben Generationen verbunden: \u2705 Erinnerungen schicken \u2705 Gro\u00dfe Auswahl an Unterhaltung",
        "headline": "Kein Kauf, keine Einrichtung.",
        "cta": null,
        "platforms": [],
        "impression_lower": null,
        "impression_upper": null,
        "start_date": "2026-02-11",
        "stop_date": null,
        "days_running": 91
      },
      {
        "competitor": "Enna",
        "ad_id": "1705688694195534",
        "status": "Active",
        "page_name": "enna.care",
        "ad_copy": "Mach auch deine Oma gl\u00fccklich & bring die ganze Familie n\u00e4her zusammen! \ud83e\udd70 \u2705 Erinnerungen & Nachrichten schicken \u2705 Gro\u00dfe Auswahl an Unterhaltung",
        "headline": "Kein Kauf, keine Einrichtung.",
        "cta": null,
        "platforms": [],
        "impression_lower": null,
        "impression_upper": null,
        "start_date": "2026-04-23",
        "stop_date": null,
        "days_running": 20
      },
      {
        "competitor": "Enna",
        "ad_id": "902105409048760",
        "status": "Active",
        "page_name": "enna.care",
        "ad_copy": "Mach auch deine Oma gl\u00fccklich & bring die ganze Familie n\u00e4her zusammen! \ud83e\udd70 \u2705 Erinnerungen & Nachrichten schicken \u2705 Gro\u00dfe Auswahl an Unterhaltung",
        "headline": "Kein Kauf, keine Einrichtung.",
        "cta": null,
        "platforms": [],
        "impression_lower": null,
        "impression_upper": null,
        "start_date": "2025-12-22",
        "stop_date": null,
        "days_running": 142
      },
      {
        "competitor": "Enna",
        "ad_id": "1893837991150333",
        "status": "Active",
        "page_name": "enna.care",
        "ad_copy": "Jetzt enna 30 Tage kostenlos testen! \ud83c\udf81 Videocalls, Lieblingssendungen oder digitaler Terminkalender: enna holt die sch\u00f6nen Seiten moderner Technik ins Wohnzimmer deiner Gro\u00dfeltern \u2013 ganz ohne Technikstress. \u2728 Was enna m\u00f6glich macht:",
        "headline": "\u2705 Digitale Fotoalben f\u00fcr gemeinsame Momente",
        "cta": null,
        "platforms": [],
        "impression_lower": null,
        "impression_upper": null,
        "start_date": "2026-04-20",
        "stop_date": null,
        "days_running": 23
      },
      {
        "competitor": "Enna",
        "ad_id": "897235946340318",
        "status": "Active",
        "page_name": "enna.care",
        "ad_copy": "\u2764\ufe0f 30.000+ Nutzer \ud83d\udcac 4000+ Bewertungen \u2b50\ufe0f 4,7 Sterne Bewertung",
        "headline": "\u2b50\ufe0f 4,7 Sterne Bewertung",
        "cta": "Learn More",
        "platforms": [],
        "impression_lower": null,
        "impression_upper": null,
        "start_date": "2026-02-06",
        "stop_date": null,
        "days_running": 96
      },
      {
        "competitor": "Enna",
        "ad_id": "779093165203295",
        "status": "Active",
        "page_name": "enna.care",
        "ad_copy": "\u2764\ufe0f 30.000+ Nutzer \ud83d\udcac 4000+ Bewertungen \u2b50\ufe0f 4,7 Sterne Bewertung",
        "headline": "\u2b50\ufe0f 4,7 Sterne Bewertung",
        "cta": "Learn More",
        "platforms": [],
        "impression_lower": null,
        "impression_upper": null,
        "start_date": "2025-12-23",
        "stop_date": null,
        "days_running": 141
      },
      {
        "competitor": "Enna",
        "ad_id": "2432986537128639",
        "status": "Active",
        "page_name": "enna.care",
        "ad_copy": "\u27a1\ufe0f Jetzt bestellen und unvergessliche Momente mit der Familie schaffen. \u27a1\ufe0f Einfach risikofrei 30 Tage kostenlos testen. Nie wieder Sorgen um Oma machen m\u00fcssen \u2764\ufe0f",
        "headline": "Nie wieder Sorgen um Oma machen m\u00fcssen \u2764\ufe0f",
        "cta": "Learn more",
        "platforms": [],
        "impression_lower": null,
        "impression_upper": null,
        "start_date": "2026-05-06",
        "stop_date": null,
        "days_running": 7
      },
      {
        "competitor": "Enna",
        "ad_id": "1492414075919509",
        "status": "Active",
        "page_name": "enna.care",
        "ad_copy": "Mach auch deine Oma gl\u00fccklich & bring die ganze Familie n\u00e4her zusammen! \ud83e\udd70 \u2705 Erinnerungen & Nachrichten schicken \u2705 Gro\u00dfe Auswahl an Unterhaltung",
        "headline": "Kein Kauf, keine Einrichtung.",
        "cta": null,
        "platforms": [],
        "impression_lower": null,
        "impression_upper": null,
        "start_date": "2026-02-06",
        "stop_date": null,
        "days_running": 96
      },
      {
        "competitor": "Enna",
        "ad_id": "4227670180779906",
        "status": "Active",
        "page_name": "enna.care",
        "ad_copy": "Mit enna bleiben Generationen verbunden: \u2705 Erinnerungen schicken \u2705 Gro\u00dfe Auswahl an Unterhaltung",
        "headline": "Kein Kauf, keine Einrichtung.",
        "cta": null,
        "platforms": [],
        "impression_lower": null,
        "impression_upper": null,
        "start_date": "2026-02-14",
        "stop_date": null,
        "days_running": 88
      },
      {
        "competitor": "Enna",
        "ad_id": "2174701993360291",
        "status": "Active",
        "page_name": "enna.care",
        "ad_copy": "Mach auch deine Oma gl\u00fccklich & bring die ganze Familie n\u00e4her zusammen! \ud83e\udd70 \u2705 Erinnerungen & Nachrichten schicken \u2705 Gro\u00dfe Auswahl an Unterhaltung",
        "headline": "Kein Kauf, keine Einrichtung.",
        "cta": null,
        "platforms": [],
        "impression_lower": null,
        "impression_upper": null,
        "start_date": "2026-02-10",
        "stop_date": null,
        "days_running": 92
      },
      {
        "competitor": "Enna",
        "ad_id": "1374243990908724",
        "status": "Active",
        "page_name": "enna.care",
        "ad_copy": "\u2764\ufe0f 30.000+ Nutzer \ud83d\udcac 4000+ Bewertungen \u2b50\ufe0f 4,7 Sterne Bewertung",
        "headline": "\u2b50\ufe0f 4,7 Sterne Bewertung",
        "cta": "Learn More",
        "platforms": [],
        "impression_lower": null,
        "impression_upper": null,
        "start_date": "2025-12-22",
        "stop_date": null,
        "days_running": 142
      },
      {
        "competitor": "Enna",
        "ad_id": "1437805007668154",
        "status": "Active",
        "page_name": "enna.care",
        "ad_copy": "Jetzt enna 30 Tage kostenlos testen! \ud83c\udf81 Videocalls, Lieblingssendungen oder digitaler Terminkalender: enna holt die sch\u00f6nen Seiten moderner Technik ins Wohnzimmer deiner Gro\u00dfeltern \u2013 ganz ohne Technikstress. \u2728 Was enna m\u00f6glich macht:",
        "headline": "\u2705 Digitale Fotoalben f\u00fcr gemeinsame Momente",
        "cta": null,
        "platforms": [],
        "impression_lower": null,
        "impression_upper": null,
        "start_date": "2026-04-20",
        "stop_date": null,
        "days_running": 23
      },
      {
        "competitor": "Enna",
        "ad_id": "865469909221216",
        "status": "Active",
        "page_name": "enna.care",
        "ad_copy": "Mach auch deine Oma gl\u00fccklich & bring die ganze Familie n\u00e4her zusammen! \ud83e\udd70 \u2705 Erinnerungen & Nachrichten schicken \u2705 Gro\u00dfe Auswahl an Unterhaltung",
        "headline": "Kein Kauf, keine Einrichtung.",
        "cta": null,
        "platforms": [],
        "impression_lower": null,
        "impression_upper": null,
        "start_date": "2025-12-22",
        "stop_date": null,
        "days_running": 142
      },
      {
        "competitor": "Enna",
        "ad_id": "3950237901786277",
        "status": "Active",
        "page_name": "enna.care",
        "ad_copy": "Mach auch deine Oma gl\u00fccklich & bring die ganze Familie n\u00e4her zusammen! \ud83e\udd70 \u2705 Erinnerungen & Nachrichten schicken \u2705 Gro\u00dfe Auswahl an Unterhaltung",
        "headline": "Kein Kauf, keine Einrichtung.",
        "cta": null,
        "platforms": [],
        "impression_lower": null,
        "impression_upper": null,
        "start_date": "2025-12-22",
        "stop_date": null,
        "days_running": 142
      },
      {
        "competitor": "Enna",
        "ad_id": "837988442409867",
        "status": "Active",
        "page_name": "enna.care",
        "ad_copy": "Mit enna bleiben Generationen verbunden: \u2705 Erinnerungen schicken \u2705 Gro\u00dfe Auswahl an Unterhaltung",
        "headline": "Kein Kauf, keine Einrichtung.",
        "cta": null,
        "platforms": [],
        "impression_lower": null,
        "impression_upper": null,
        "start_date": "2025-11-07",
        "stop_date": null,
        "days_running": 187
      },
      {
        "competitor": "Enna",
        "ad_id": "1172331531410149",
        "status": "Active",
        "page_name": "enna.care",
        "ad_copy": "Mach auch deine Oma gl\u00fccklich & bring die ganze Familie n\u00e4her zusammen! \ud83e\udd70 \u2705 Erinnerungen & Nachrichten schicken \u2705 Gro\u00dfe Auswahl an Unterhaltung",
        "headline": "Kein Kauf, keine Einrichtung.",
        "cta": null,
        "platforms": [],
        "impression_lower": null,
        "impression_upper": null,
        "start_date": "2026-02-10",
        "stop_date": null,
        "days_running": 92
      },
      {
        "competitor": "Enna",
        "ad_id": "1512919597145913",
        "status": "Active",
        "page_name": "enna.care",
        "ad_copy": "Mach auch deine Oma gl\u00fccklich & bring die ganze Familie n\u00e4her zusammen! \ud83e\udd70 \u2705 Erinnerungen & Nachrichten schicken \u2705 Gro\u00dfe Auswahl an Unterhaltung",
        "headline": "Kein Kauf, keine Einrichtung.",
        "cta": null,
        "platforms": [],
        "impression_lower": null,
        "impression_upper": null,
        "start_date": "2026-04-22",
        "stop_date": null,
        "days_running": 21
      },
      {
        "competitor": "Enna",
        "ad_id": "1399231441610269",
        "status": "Active",
        "page_name": "enna.care",
        "ad_copy": "\u27a1\ufe0f Jetzt bestellen und unvergessliche Momente mit der Familie schaffen. \u27a1\ufe0f Einfach risikofrei 30 Tage kostenlos testen",
        "headline": "\u27a1\ufe0f Einfach risikofrei 30 Tage kostenlos testen",
        "cta": "Learn More",
        "platforms": [],
        "impression_lower": null,
        "impression_upper": null,
        "start_date": "2025-12-22",
        "stop_date": null,
        "days_running": 142
      },
      {
        "competitor": "Enna",
        "ad_id": "845708628516759",
        "status": "Active",
        "page_name": "enna.care",
        "ad_copy": "Mach auch deine Oma gl\u00fccklich & bring die ganze Familie n\u00e4her zusammen! \ud83e\udd70 \u2705 Erinnerungen & Nachrichten schicken \u2705 Gro\u00dfe Auswahl an Unterhaltung",
        "headline": "Kein Kauf, keine Einrichtung.",
        "cta": null,
        "platforms": [],
        "impression_lower": null,
        "impression_upper": null,
        "start_date": "2026-02-10",
        "stop_date": null,
        "days_running": 92
      },
      {
        "competitor": "Enna",
        "ad_id": "3062325337310484",
        "status": "Active",
        "page_name": "enna.care",
        "ad_copy": "Mach auch deine Oma gl\u00fccklich & bring die ganze Familie n\u00e4her zusammen! \ud83e\udd70 \u2705 Erinnerungen & Nachrichten schicken \u2705 Gro\u00dfe Auswahl an Unterhaltung",
        "headline": "Kein Kauf, keine Einrichtung.",
        "cta": null,
        "platforms": [],
        "impression_lower": null,
        "impression_upper": null,
        "start_date": "2026-04-20",
        "stop_date": null,
        "days_running": 23
      },
      {
        "competitor": "Enna",
        "ad_id": "4242129459386641",
        "status": "Active",
        "page_name": "enna.care",
        "ad_copy": "Das sagt Oma Rita \u00fcber enna \ud83e\udd70 \u27a1\ufe0f Jetzt bestellen und unvergessliche Momente mit der Familie schaffen. \u27a1\ufe0f Einfach risikofrei 30 Tage kostenlos testen.",
        "headline": "30 Tage kostenlos testen",
        "cta": null,
        "platforms": [],
        "impression_lower": null,
        "impression_upper": null,
        "start_date": "2025-12-22",
        "stop_date": null,
        "days_running": 142
      },
      {
        "competitor": "Enna",
        "ad_id": "1261259292795309",
        "status": "Active",
        "page_name": "enna.care",
        "ad_copy": "Mach auch deine Oma gl\u00fccklich & bring die ganze Familie n\u00e4her zusammen! \ud83e\udd70 \u2705 Erinnerungen & Nachrichten schicken \u2705 Gro\u00dfe Auswahl an Unterhaltung",
        "headline": "Kein Kauf, keine Einrichtung.",
        "cta": null,
        "platforms": [],
        "impression_lower": null,
        "impression_upper": null,
        "start_date": "2026-04-22",
        "stop_date": null,
        "days_running": 21
      },
      {
        "competitor": "Enna",
        "ad_id": "1569175130960103",
        "status": "Active",
        "page_name": "enna.care",
        "ad_copy": "Mit enna bleiben Generationen verbunden: \u2705 Erinnerungen schicken \u2705 Gro\u00dfe Auswahl an Unterhaltung",
        "headline": "Kein Kauf, keine Einrichtung.",
        "cta": null,
        "platforms": [],
        "impression_lower": null,
        "impression_upper": null,
        "start_date": "2026-02-11",
        "stop_date": null,
        "days_running": 91
      },
      {
        "competitor": "Enna",
        "ad_id": "1936681396916523",
        "status": "Active",
        "page_name": "enna.care",
        "ad_copy": "Mach auch deine Oma gl\u00fccklich & bring die ganze Familie n\u00e4her zusammen! \ud83e\udd70 \u27a1\ufe0f Jetzt bestellen und & risikofrei 30 Tage kostenlos testen!",
        "headline": "\u27a1\ufe0f Jetzt bestellen und & risikofrei 30 Tage kostenlos testen!",
        "cta": "Learn More",
        "platforms": [],
        "impression_lower": null,
        "impression_upper": null,
        "start_date": "2025-12-22",
        "stop_date": null,
        "days_running": 142
      },
      {
        "competitor": "Enna",
        "ad_id": "1679733286792787",
        "status": "Active",
        "page_name": "enna.care",
        "ad_copy": "Mach auch deine Oma gl\u00fccklich & bring die ganze Familie n\u00e4her zusammen! \ud83e\udd70 \u2705 Erinnerungen & Nachrichten schicken \u2705 Gro\u00dfe Auswahl an Unterhaltung",
        "headline": "Kein Kauf, keine Einrichtung.",
        "cta": null,
        "platforms": [],
        "impression_lower": null,
        "impression_upper": null,
        "start_date": "2026-04-22",
        "stop_date": null,
        "days_running": 21
      },
      {
        "competitor": "Enna",
        "ad_id": "2141039749998490",
        "status": "Active",
        "page_name": "enna.care",
        "ad_copy": "Mach auch deine Oma gl\u00fccklich & bring die ganze Familie n\u00e4her zusammen! \ud83e\udd70 \u2705 Erinnerungen & Nachrichten schicken \u2705 Gro\u00dfe Auswahl an Unterhaltung",
        "headline": "Kein Kauf, keine Einrichtung.",
        "cta": null,
        "platforms": [],
        "impression_lower": null,
        "impression_upper": null,
        "start_date": "2026-02-10",
        "stop_date": null,
        "days_running": 92
      },
      {
        "competitor": "Enna",
        "ad_id": "1596863971606242",
        "status": "Active",
        "page_name": "enna.care",
        "ad_copy": "Jetzt enna 30 Tage kostenlos testen! \ud83c\udf81 Videocalls, Lieblingssendungen oder digitaler Terminkalender: enna holt die sch\u00f6nen Seiten moderner Technik ins Wohnzimmer deiner Gro\u00dfeltern \u2013 ganz ohne Technikstress. \u2728 Was enna m\u00f6glich macht:",
        "headline": "\u2705 Digitale Fotoalben f\u00fcr gemeinsame Momente",
        "cta": null,
        "platforms": [],
        "impression_lower": null,
        "impression_upper": null,
        "start_date": "2026-04-20",
        "stop_date": null,
        "days_running": 23
      }
    ],
    "Heritage Whisper": [
      {
        "competitor": "Heritage Whisper",
        "ad_id": "1508659510855906",
        "status": "Active",
        "page_name": "Heritage Whisper",
        "ad_copy": "Voice-first memory sharing Voice-first memory sharing Storytelling that is captivating families worldwide",
        "headline": "Storytelling that is captivating families worldwide",
        "cta": "Learn More",
        "platforms": [],
        "impression_lower": null,
        "impression_upper": null,
        "start_date": "2026-04-19",
        "stop_date": null,
        "days_running": 24
      }
    ]
  }
}